Metadata-Version: 2.1
Name: jsonstrip
Version: 22.10.20
Summary: A Python module for stripping comments from JSON
Home-page: https://github.com/xitop/jsonstrip
Author: Vlado Potisk
Author-email: jsonstrip@poti.sk
License: UNKNOWN
Project-URL: Source, https://github.com/xitop/jsonstrip/
Platform: UNKNOWN
Classifier: Development Status :: 5 - Production/Stable
Classifier: Intended Audience :: Developers
Classifier: Topic :: Text Processing :: Filters
Classifier: Topic :: Software Development :: Libraries :: Python Modules
Classifier: License :: OSI Approved :: MIT License
Classifier: Programming Language :: Python :: 3
Classifier: Programming Language :: Python :: 3.7
Classifier: Programming Language :: Python :: 3.8
Classifier: Programming Language :: Python :: 3.9
Classifier: Programming Language :: Python :: 3.10
Requires-Python: >=3.7
License-File: LICENSE.txt
